kilroy_face_twitter/__init__.py
kilroy_face_twitter/__main__.py
kilroy_face_twitter/client.py
kilroy_face_twitter/config.py
kilroy_face_twitter/data.py
kilroy_face_twitter/face.py
kilroy_face_twitter/log.py
kilroy_face_twitter/models.py
kilroy_face_twitter/post.py
kilroy_face_twitter/posters.py
kilroy_face_twitter/processors.py
kilroy_face_twitter/resources/__init__.py
kilroy_face_twitter/resources/config.yaml
kilroy_face_twitter/restrictions.py
kilroy_face_twitter/scoring/__init__.py
kilroy_face_twitter/scoring/modifiers.py
kilroy_face_twitter/scoring/raw.py
kilroy_face_twitter/scrapers.py
kilroy_face_twitter/utils.py
kilroy_face_twitter-0.6.4.dist-info/entry_points.txt
kilroy_face_twitter-0.6.4.dist-info/LICENSE
kilroy_face_twitter-0.6.4.dist-info/WHEEL
kilroy_face_twitter-0.6.4.dist-info/METADATA
kilroy_face_twitter-0.6.4.dist-info/RECORD
