Metadata-Version: 2.1
Name: kilroy-face-twitter
Version: 0.6.4
Summary: kilroy face for Twitter 🐦
Home-page: https://github.com/kilroybot/kilroy-face-twitter
Author: kilroy
Author-email: kilroymail@pm.me
Requires-Python: >=3.10,<4.0
Classifier: License :: OSI Approved :: MIT License
Classifier: Operating System :: OS Independent
Classifier: Programming Language :: Python :: 3
Classifier: Programming Language :: Python :: 3.10
Requires-Dist: detoxify (>=0.5,<0.6)
Requires-Dist: httpx (>=0.23,<0.24)
Requires-Dist: kilroy-face-server-py-sdk (>=0.9,<0.10)
Requires-Dist: numpy (>=1.23,<2.0)
Requires-Dist: omegaconf (>=2.2,<3.0)
Requires-Dist: platformdirs (>=2.5,<3.0)
Requires-Dist: pydantic[dotenv] (>=1.10,<2.0)
Requires-Dist: tweepy[async] (>=4.10,<5.0)
Requires-Dist: typer[all] (>=0.6,<0.7)
Project-URL: Documentation, https://kilroybot.github.io/kilroy-face-twitter
Project-URL: Repository, https://github.com/kilroybot/kilroy-face-twitter
